droidrun_mcp/__init__.py
droidrun_mcp/runner.py
droidrun_mcp/server.py
droidrun_mcp-0.1.5.dist-info/METADATA
droidrun_mcp-0.1.5.dist-info/WHEEL
droidrun_mcp-0.1.5.dist-info/entry_points.txt
droidrun_mcp-0.1.5.dist-info/RECORD
