Metadata-Version: 2.4
Name: droidrun-mcp
Version: 0.1.5
Summary: MCP Server for Droidrun
Project-URL: Homepage, https://github.com/droidrun/droidrun-mcp
Project-URL: Repository, https://github.com/droidrun/droidrun-mcp
Author-email: Rasul Osmanbayli <rasul.osmanbeyli@gmail.com>
License: MIT
Requires-Python: >=3.10
Requires-Dist: droidrun[anthropic,google,langfuse,openai]==0.4.14
Requires-Dist: fastmcp
Requires-Dist: pillow
